object_storage/__init__.py
object_storage/clients/__init__.py
object_storage/clients/azure_blob_client.py
object_storage/clients/azure_container_client.py
object_storage/clients/base_container_client.py
object_storage/clients/base_file_client.py
object_storage/config.py
object_storage/factories.py
object_storage/managers/__init__.py
object_storage/managers/azure_blob_manager.py
object_storage/managers/base_manager.py
object_storage/providers/__init__.py
object_storage/providers/azure.py
object_storage/providers/enum.py
object_storage/providers/gcp/__init__.py
object_storage/providers/gcp/bucket_client.py
object_storage/providers/gcp/model.py
object_storage/providers/gcp/object_client.py
pilot_platform_object_storage-2.0.0.dist-info/METADATA
pilot_platform_object_storage-2.0.0.dist-info/WHEEL
pilot_platform_object_storage-2.0.0.dist-info/RECORD
