Metadata-Version: 2.3
Name: pilot-platform-object-storage
Version: 2.0.0
Summary: Python library for interacting with multiple object storage APIs.
License: Proprietary
Author: Indoc Systems
Requires-Python: >=3.10,<3.13
Classifier: License :: Other/Proprietary License
Classifier: Operating System :: OS Independent
Classifier: Programming Language :: Python :: 3
Classifier: Programming Language :: Python :: 3.10
Classifier: Programming Language :: Python :: 3.11
Classifier: Programming Language :: Python :: 3.12
Requires-Dist: aiofiles (>=24.1.0,<25.0.0)
Requires-Dist: aiogoogle (==5.13.0)
Requires-Dist: aiohttp (>=3.12.15,<4.0.0)
Requires-Dist: azure-storage-blob (>=12.26.0,<13.0.0)
Requires-Dist: google-cloud-storage (>=3.3.1,<4.0.0)
Requires-Dist: google-resumable-media (>=2.7.2,<3.0.0)
Requires-Dist: pydantic (>=2.7.1,<3.0.0)
Requires-Dist: pytest-httpx (>=0.35.0,<0.36.0)
Project-URL: Documentation, https://pilotdataplatform.github.io/object-storage/
